fmtparse/__init__.py
fmtparse/printf.py
fmtparse/version.py
fmtparse/wellknown.py
fmtparse-0.1.dev0.dist-info/METADATA
fmtparse-0.1.dev0.dist-info/WHEEL
fmtparse-0.1.dev0.dist-info/top_level.txt
fmtparse-0.1.dev0.dist-info/zip-safe
fmtparse-0.1.dev0.dist-info/RECORD
